<?xml version = '1.0' encoding = 'UTF-8'?>
<FKIndexAssociation class="oracle.dbtools.crest.model.design.relational.FKIndexAssociation" directorySegmentName="seg_0" id="D1FBEA56-5E34-4EE8-8491-FD2EBB6390F2" containerWithKeyObject="179EBA1B-0F45-2F74-F0A3-41F149259440" localFKIndex="B8FBADD1-F72C-43B6-C9BB-D71D84F058FA" name="bitacora_usuario">
<createdBy>Asus Zenbook</createdBy>
<createdTime>2023-02-17 04:20:46 UTC</createdTime>
<ownerDesignName>1-DataModel_Clientes</ownerDesignName>
<referredTableLongName>usuario</referredTableLongName>
<deleteRule>NO ACTION</deleteRule>
<referredTableID>80A5AB27-5DB4-7AAE-9605-80DF3B13D51A</referredTableID>
<keyObject>B8185A9E-5470-6B2C-AFE8-22CD31E3FCFB</keyObject>
<referredKeyID>B8185A9E-5470-6B2C-AFE8-22CD31E3FCFB</referredKeyID>
<mandatory>true</mandatory>
<refColNames>cui</refColNames>
<transferable>true</transferable>
<rely>false</rely>
<columnDependencyConstraintGenerateInDDL>true</columnDependencyConstraintGenerateInDDL>
</FKIndexAssociation>